ciphersweet.py
ciphersweet-0.1.1.dist-info/LICENSE
ciphersweet-0.1.1.dist-info/WHEEL
ciphersweet-0.1.1.dist-info/METADATA
ciphersweet-0.1.1.dist-info/RECORD
