Metadata-Version: 2.1
Name: ciphersweet
Version: 0.1.1
Summary: Python implementation of ciphersweet
Home-page: https://github.com/rlittlefield/pyciphersweet
License: MIT
Author: J. Ryan Littlefield
Author-email: ryan@ryanlittlefield.com
Classifier: License :: OSI Approved :: MIT License
Classifier: Programming Language :: Python :: 2
Classifier: Programming Language :: Python :: 2.7
Classifier: Programming Language :: Python :: 3
Classifier: Programming Language :: Python :: 3.4
Classifier: Programming Language :: Python :: 3.5
Classifier: Programming Language :: Python :: 3.6
Classifier: Programming Language :: Python :: 3.7
Requires-Dist: cryptography (>=2.3,<3.0)
Requires-Dist: pysodium (>=0.7.0,<0.8.0)
